admin_tools/__init__.py
admin_tools/apps.py
admin_tools/checks.py
admin_tools/deprecate_utils.py
admin_tools/models.py
admin_tools/template_loaders.py
admin_tools/tests.py
admin_tools/urls.py
admin_tools/utils.py
admin_tools/dashboard/__init__.py
admin_tools/dashboard/apps.py
admin_tools/dashboard/dashboards.py
admin_tools/dashboard/forms.py
admin_tools/dashboard/models.py
admin_tools/dashboard/modules.py
admin_tools/dashboard/registry.py
admin_tools/dashboard/tests.py
admin_tools/dashboard/urls.py
admin_tools/dashboard/utils.py
admin_tools/dashboard/views.py
admin_tools/dashboard/management/__init__.py
admin_tools/dashboard/management/commands/__init__.py
admin_tools/dashboard/management/commands/clear_dashboard_preferences.py
admin_tools/dashboard/management/commands/customdashboard.py
admin_tools/dashboard/migrations/0001_initial.py
admin_tools/dashboard/migrations/__init__.py
admin_tools/dashboard/south_migrations/0001_initial.py
admin_tools/dashboard/south_migrations/0002_auto__add_field_dashboardpreferences_dashboard_id.py
admin_tools/dashboard/south_migrations/0003_auto__add_unique_dashboardpreferences_dashboard_id_user.py
admin_tools/dashboard/south_migrations/__init__.py
admin_tools/dashboard/static/admin_tools/css/dashboard-ie.css
admin_tools/dashboard/static/admin_tools/css/dashboard.css
admin_tools/dashboard/static/admin_tools/css/jquery/jquery-ui.css
admin_tools/dashboard/static/admin_tools/css/jquery/images/animated-overlay.gif
admin_tools/dashboard/static/admin_tools/css/jquery/images/ui-bg_flat_0_aaaaaa_40x100.png
admin_tools/dashboard/static/admin_tools/css/jquery/images/ui-bg_flat_75_ffffff_40x100.png
admin_tools/dashboard/static/admin_tools/css/jquery/images/ui-bg_glass_55_fbf9ee_1x400.png
admin_tools/dashboard/static/admin_tools/css/jquery/images/ui-bg_glass_65_ffffff_1x400.png
admin_tools/dashboard/static/admin_tools/css/jquery/images/ui-bg_glass_75_dadada_1x400.png
django_admin_better_tools-0.1.0.dist-info/LICENSE
django_admin_better_tools-0.1.0.dist-info/METADATA
django_admin_better_tools-0.1.0.dist-info/WHEEL
django_admin_better_tools-0.1.0.dist-info/top_level.txt
django_admin_better_tools-0.1.0.dist-info/RECORD
